pyscopus/APIURI.py
pyscopus/__init__.py
pyscopus/scopus.py
pyscopus/utils.py
pyscopus-1.0.2.dist-info/METADATA
pyscopus-1.0.2.dist-info/RECORD
pyscopus-1.0.2.dist-info/WHEEL
pyscopus-1.0.2.dist-info/top_level.txt
