Metadata-Version: 2.1
Name: pyscopus
Version: 1.0.2
Summary: A Python wrapper for Scopus API
Home-page: http://zhiyzuo.github.io/python-scopus/
Author: Zhiya Zuo
Author-email: zhiyazuo@gmail.com
License: MIT
Download-URL: https://github.com/zhiyzuo/python-scopus/tarball/1.0.2
Keywords: scopus python api document retrieval information scholar academic
Platform: UNKNOWN
Classifier: Development Status :: 3 - Alpha
Classifier: Intended Audience :: Education
Classifier: Intended Audience :: Science/Research
Classifier: Intended Audience :: Information Technology
Classifier: Topic :: Text Editors :: Text Processing
Classifier: Topic :: Scientific/Engineering :: Information Analysis
Classifier: Topic :: Education
Classifier: Topic :: Utilities
Classifier: Operating System :: MacOS
Classifier: Operating System :: Unix
Classifier: License :: OSI Approved :: MIT License
Classifier: Programming Language :: Python :: 2.7
Classifier: Programming Language :: Python :: 3.6
